[
  {
    "Ticker": "VAE.AX",
    "Name": "Vanguard FTSE Asia ex Japan Shares Index ETF",
    "Price (AUD)": 89.17,
    "Average 10-day Volume": 12269,
    "YTD Return (%)": 12.01825,
    "3Y Return (%)": 13.15,
    "5Y Return (%)": 7.1,
    "P/E Ratio": 16.0858,
    "Dividend Yield": 2.06,
    "52 Week High": 91.79,
    "52 Week Low": 72.01,
    "Inception Date": "2015-12-09",
    "Updated": "2025-09-05 06:34"
  },
  {
    "Ticker": "ASIA.AX",
    "Name": "BetaShares Asia Technology Tigers ETF",
    "Price (AUD)": 12.45,
    "Average 10-day Volume": 161442,
    "YTD Return (%)": 21.20217,
    "3Y Return (%)": 22.08,
    "5Y Return (%)": 6.44,
    "P/E Ratio": 20.574234,
    "Dividend Yield": 0.72,
    "52 Week High": 12.76,
    "52 Week Low": 8.42,
    "Inception Date": "2018-09-18",
    "Updated": "2025-09-05 06:34"
  },
  {
    "Ticker": "IAA.AX",
    "Name": "iShares Asia 50 ETF (AU)",
    "Price (AUD)": 127.36,
    "Average 10-day Volume": 13508,
    "YTD Return (%)": 18.75763,
    "3Y Return (%)": 17.71,
    "5Y Return (%)": 7.42,
    "P/E Ratio": 14.398927,
    "Dividend Yield": 4.05,
    "52 Week High": 130.91,
    "52 Week Low": 95.27,
    "Inception Date": "2007-11-13",
    "Updated": "2025-09-05 06:34"
  },
  {
    "Ticker": "YMAX.AX",
    "Name": "Betashares Australian Top 20 Equities Yield Maximiser Complex ETF",
    "Price (AUD)": 7.82,
    "Average 10-day Volume": 91134,
    "YTD Return (%)": null,
    "3Y Return (%)": null,
    "5Y Return (%)": null,
    "P/E Ratio": 18.947565,
    "Dividend Yield": null,
    "52 Week High": 8.14,
    "52 Week Low": 6.79,
    "Inception Date": null,
    "Updated": "2025-09-05 06:34"
  },
  {
    "Ticker": "SYI.AX",
    "Name": "SPDR MSCI Australia Select High Dividend Yield ETF",
    "Price (AUD)": 30.48,
    "Average 10-day Volume": 23578,
    "YTD Return (%)": 11.54559,
    "3Y Return (%)": 13.05,
    "5Y Return (%)": 13.3,
    "P/E Ratio": 17.158833,
    "Dividend Yield": 12.75,
    "52 Week High": 31.43,
    "52 Week Low": 25.99,
    "Inception Date": "2010-09-28",
    "Updated": "2025-09-05 06:34"
  },
  {
    "Ticker": "ZYAU.AX",
    "Name": "Global X S&P/ASX 200 High Dividend ETF",
    "Price (AUD)": 9.76,
    "Average 10-day Volume": 7471,
    "YTD Return (%)": 9.24541,
    "3Y Return (%)": 10.4,
    "5Y Return (%)": 6.33,
    "P/E Ratio": 14.839532,
    "Dividend Yield": 4.42,
    "52 Week High": 9.88,
    "52 Week Low": 7.73,
    "Inception Date": "2015-06-10",
    "Updated": "2025-09-05 06:34"
  },
  {
    "Ticker": "NDQ.AX",
    "Name": "BetaShares NASDAQ 100 ETF",
    "Price (AUD)": 52.91,
    "Average 10-day Volume": 259640,
    "YTD Return (%)": 6.34313,
    "3Y Return (%)": 26.05,
    "5Y Return (%)": 17.64,
    "P/E Ratio": 35.150124,
    "Dividend Yield": 0.98,
    "52 Week High": 54.12,
    "52 Week Low": 40.69,
    "Inception Date": "2020-07-20",
    "Updated": "2025-09-05 06:34"
  },
  {
    "Ticker": "MVB.AX",
    "Name": "VanEck Australian Banks ETF",
    "Price (AUD)": 42.81,
    "Average 10-day Volume": 11786,
    "YTD Return (%)": 8.67863,
    "3Y Return (%)": 20.68,
    "5Y Return (%)": 22.09,
    "P/E Ratio": 20.062716,
    "Dividend Yield": 4.22,
    "52 Week High": 43.82,
    "52 Week Low": 32.98,
    "Inception Date": "2013-10-14",
    "Updated": "2025-09-05 06:34"
  }
]